{
	"name": "CopyPipeline_CopyQSEtoDim",
	"properties": {
		"activities": [
			{
				"name": "Copy_how",
				"type": "Copy",
				"dependsOn": [],
				"policy": {
					"timeout": "7.00:00:00",
					"retry": 0,
					"retryIntervalInSeconds": 30,
					"secureOutput": false,
					"secureInput": false
				},
				"userProperties": [
					{
						"name": "Source",
						"value": "RawData/MICRODADOS_ENEM_2019.csv"
					},
					{
						"name": "Destination",
						"value": "dbo.Dimension_Table_QSE"
					}
				],
				"typeProperties": {
					"source": {
						"type": "DelimitedTextSource",
						"storeSettings": {
							"type": "AzureDataLakeStoreReadSettings",
							"recursive": true,
							"enablePartitionDiscovery": false
						},
						"formatSettings": {
							"type": "DelimitedTextReadSettings",
							"skipLineCount": 0
						}
					},
					"sink": {
						"type": "SqlServerSink"
					},
					"enableStaging": false,
					"validateDataConsistency": false,
					"translator": {
						"type": "TabularTranslator",
						"mappings": [
							{
								"source": {
									"name": "Q025",
									"type": "String",
									"physicalType": "String"
								},
								"sink": {
									"name": "Q025",
									"type": "String",
									"physicalType": "varchar"
								}
							}
						],
						"typeConversion": true,
						"typeConversionSettings": {
							"allowDataTruncation": true,
							"treatBooleanAsNumber": false
						}
					}
				},
				"inputs": [
					{
						"referenceName": "SourceDataset_how",
						"type": "DatasetReference"
					}
				],
				"outputs": [
					{
						"referenceName": "DestinationDataset_how",
						"type": "DatasetReference"
					}
				]
			}
		],
		"annotations": []
	}
}